yenviron/__init__.py
yenviron/exceptions.py
yenviron/yenviron.py
yenviron/test/__init__.py
yenviron/test/test.py
yenviron-0.3.dist-info/LICENSE.md
yenviron-0.3.dist-info/METADATA
yenviron-0.3.dist-info/WHEEL
yenviron-0.3.dist-info/top_level.txt
yenviron-0.3.dist-info/RECORD
